day_6/SISO_shift_register.sv
module siso_shift_register (
  input   wire clk,
  input   wire reset,

  input   wire si_i,

  output  reg [7:0] so_o
);

    always_ff @(posedge clk or posedge reset) begin : counter
        if (reset) begin
            so_o <= 8'b0;
        end else begin
            so_o <= {so_o, si_i};
        end
    end

endmodule

day_6/SISO_shift_register_tb.sv
module siso_shift_register_tb ();

    logic clk;
    logic reset;
    logic si_i;

    logic [7:0] so_o;

    siso_shift_register siso_shift_register1 (.*);
    
    always begin
        clk = 1'b1;
        #1;
        clk = 1'b0;
        #1;
    end

    initial begin
        si_i = 1'b0;
        reset = 1'b0;
        #1;
        reset = 1'b1;
        #1;
        reset = 1'b0;
        #1;

        si_i = 1'b1;
        #2;
        si_i = 1'b0;
        #1;

        for (int i = 0; i < 16; i++) begin
            $display("so_o=%b", so_o);
            #1;
        end
        $finish;
    end

    initial
    begin
        $dumpfile("test.vcd");
        $dumpvars(0,siso_shift_register_tb);
    end

endmodule

day_6/test.vcd
$date
	Fri Oct 14 19:48:27 2022
$end
$version
	Icarus Verilog
$end
$timescale
	1s
$end
$scope module siso_shift_register_tb $end
$var wire 8 ! so_o [7:0] $end
$var reg 1 " clk $end
$var reg 1 # reset $end
$var reg 1 $ si_i $end
$scope module siso_shift_register1 $end
$var wire 1 " clk $end
$var wire 1 # reset $end
$var wire 1 $ si_i $end
$var reg 8 % so_o [7:0] $end
$scope begin counter $end
$upscope $end
$upscope $end
$scope begin $ivl_for_loop0 $end
$var integer 32 & i [31:0] $end
$upscope $end
$upscope $end
$enddefinitions $end
$comment Show the parameter values. $end
$dumpall
$end
#0
$dumpvars
b0 &
bx0 %
0$
0#
1"
bx0 !
$end
#1
b0 !
b0 %
1#
0"
#2
0#
1"
#3
1$
0"
#4
b1 !
b1 %
1"
#5
0"
0$
#6
b10 !
b10 %
1"
#7
0"
b1 &
#8
b100 !
b100 %
1"
b10 &
#9
0"
b11 &
#10
b1000 !
b1000 %
1"
b100 &
#11
0"
b101 &
#12
b10000 !
b10000 %
1"
b110 &
#13
0"
b111 &
#14
b100000 !
b100000 %
1"
b1000 &
#15
0"
b1001 &
#16
b1000000 !
b1000000 %
1"
b1010 &
#17
0"
b1011 &
#18
b10000000 !
b10000000 %
1"
b1100 &
#19
0"
b1101 &
#20
b0 !
b0 %
1"
b1110 &
#21
0"
b1111 &
#22
1"
b10000 &
